battetl/BattETL.py
battetl/__init__.py
battetl/battetl_quick.py
battetl/constants.py
battetl/logger.py
battetl/utils.py
battetl/extract/Extractor.py
battetl/extract/__init__.py
battetl/load/Loader.py
battetl/load/__init__.py
battetl/load/batt_db_test_helper.py
battetl/load/quick_loader.py
battetl/transform/Transformer.py
battetl/transform/__init__.py
battetl-1.1.19.dist-info/LICENSE
battetl-1.1.19.dist-info/METADATA
battetl-1.1.19.dist-info/WHEEL
battetl-1.1.19.dist-info/entry_points.txt
battetl-1.1.19.dist-info/top_level.txt
battetl-1.1.19.dist-info/RECORD
