Metadata-Version: 2.1
Name: battetl
Version: 1.1.19
Summary: A Python module for extracting, transforming, and loading battery data to a database.
Home-page: https://github.com/BattGenie/battetl
Author: Zander Nevitt, Bing Syuan Wang, Eric Ravet, Aditya Parsai and Chintan Pathak
Author-email: info@battgenie.life
License: MIT
Classifier: Programming Language :: Python :: 3
Classifier: License :: OSI Approved :: MIT License
Classifier: Operating System :: OS Independent
Requires-Python: >=3.9, <3.12
License-File: LICENSE
Requires-Dist: python-dotenv >=1.0.0
Requires-Dist: pandas <2.2.0,>=1.3.0
Requires-Dist: sqlalchemy <2.0.0,>=1.4.20
Requires-Dist: psycopg2-binary ==2.9.6
Requires-Dist: pydash ==6.0.0
Requires-Dist: xmltodict ==0.12.0
Requires-Dist: schema ==0.7.5
Requires-Dist: pyyaml >=5.4.1
Requires-Dist: configparser ==5.3.0
Requires-Dist: tqdm >=4.62.3
